Metadata-Version: 2.1
Name: txZMQ-ng
Version: 1.0.3
Summary: Twisted bindings for ZeroMQ
Download-URL: https://pypi.org/project/txZMQ-ng/
Author: Andrey Smirnov
Author-email: me@smira.ru
Maintainer: William Barnhart
Maintainer-email: williambbarnhart@gmail.com
Classifier: Programming Language :: Python
Classifier: Programming Language :: Python :: 3
Classifier: Development Status :: 5 - Production/Stable
Classifier: Intended Audience :: Developers
Classifier: Natural Language :: English
Classifier: License :: OSI Approved :: Mozilla Public License 2.0 (MPL 2.0)
Classifier: Topic :: Software Development :: Libraries
License-File: LICENSE.txt
License-File: AUTHORS.txt
Requires-Dist: Twisted (>=10.0)
Requires-Dist: pyzmq (>=13)
Provides-Extra: dev
Requires-Dist: Twisted ; extra == 'dev'
Requires-Dist: service-identity ; extra == 'dev'
Requires-Dist: pyzmq (>=13) ; extra == 'dev'
Requires-Dist: pyflakes ; extra == 'dev'
Requires-Dist: pycodestyle ; extra == 'dev'
Requires-Dist: Sphinx ; extra == 'dev'
Requires-Dist: coverage ; extra == 'dev'
Requires-Dist: coveralls ; extra == 'dev'
Requires-Dist: virtualenv ; extra == 'dev'
